audette/__init__.py
audette/_modidx.py
audette/core.py
audette-0.0.2.dist-info/LICENSE
audette-0.0.2.dist-info/METADATA
audette-0.0.2.dist-info/WHEEL
audette-0.0.2.dist-info/entry_points.txt
audette-0.0.2.dist-info/top_level.txt
audette-0.0.2.dist-info/RECORD
